README.rst
setup.cfg
setup.py
arduino_simple_rpc.egg-info/PKG-INFO
arduino_simple_rpc.egg-info/SOURCES.txt
arduino_simple_rpc.egg-info/dependency_links.txt
arduino_simple_rpc.egg-info/entry_points.txt
arduino_simple_rpc.egg-info/requires.txt
arduino_simple_rpc.egg-info/top_level.txt
simple_rpc/__init__.py
simple_rpc/cli.py
simple_rpc/extras.py
simple_rpc/io.py
simple_rpc/protocol.py
simple_rpc/simple_rpc.py