Metadata-Version: 1.1
Name: arduino-simple-rpc
Version: 2.3.0
Summary: Arduino simpleRPC API client library and CLI.
Home-page: https://arduino-simple-rpc.readthedocs.io
Author: Jeroen F.J. Laros
Author-email: jlaros@fixedpoint.nl
License: MIT
Platform: UNKNOWN
Classifier: Intended Audience :: Developers
Classifier: Intended Audience :: Science/Research
Classifier: Operating System :: OS Independent
Classifier: Programming Language :: Python
Classifier: Programming Language :: Python :: 3
Classifier: Programming Language :: Python :: 3.5
Classifier: Topic :: Scientific/Engineering
